wappalyzer/__init__.py
wappalyzer/__main__.py
wappalyzer/analyzers/__init__.py
wappalyzer/analyzers/dom.py
wappalyzer/analyzers/js.py
wappalyzer/browser/__init__.py
wappalyzer/browser/analyzer.py
wappalyzer/core/__init__.py
wappalyzer/core/analyzer.py
wappalyzer/core/config.py
wappalyzer/core/matcher.py
wappalyzer/core/requester.py
wappalyzer/core/utils.py
wappalyzer/data/categories.json
wappalyzer/data/groups.json
wappalyzer/data/technologies.json
wappalyzer/data/wappalyzer.xpi
wappalyzer/parsers/__init__.py
wappalyzer/parsers/certIssuer.py
wappalyzer/parsers/css.py
wappalyzer/parsers/dns.py
wappalyzer/parsers/js.py
wappalyzer/parsers/meta.py
wappalyzer/parsers/robots.py
wappalyzer/parsers/scriptSrc.py
wappalyzer-1.0.20.dist-info/licenses/LICENSE
wappalyzer-1.0.20.dist-info/METADATA
wappalyzer-1.0.20.dist-info/WHEEL
wappalyzer-1.0.20.dist-info/entry_points.txt
wappalyzer-1.0.20.dist-info/top_level.txt
wappalyzer-1.0.20.dist-info/RECORD
