Metadata-Version: 2.4
Name: wappalyzer
Version: 1.0.20
Summary: Wappalyzer-based tech stack detection library
Home-page: https://github.com/s0md3v/wappalyzer-next
Download-URL: https://github.com/s0md3v/wappalyzer-next/archive/1.0.20.zip
Author: Somdev Sangwan
Author-email: s0md3v@gmail.com
License: GNU General Public License v3
Keywords: wappalyzer,tech stack,bug bounty,pentesting,security,whatruns
Classifier: Development Status :: 5 - Production/Stable
Classifier: Intended Audience :: Developers
Classifier: Intended Audience :: Information Technology
Classifier: Operating System :: OS Independent
Classifier: Topic :: Security
Classifier: Programming Language :: Python :: 3.4
License-File: LICENSE
Requires-Dist: requests
Requires-Dist: huepy
Requires-Dist: selenium
Requires-Dist: tldextract
Requires-Dist: beautifulsoup4
Requires-Dist: dnspython
Dynamic: author
Dynamic: author-email
Dynamic: classifier
Dynamic: description
Dynamic: description-content-type
Dynamic: download-url
Dynamic: home-page
Dynamic: keywords
Dynamic: license
Dynamic: license-file
Dynamic: requires-dist
Dynamic: summary
